ixexplorer/__init__.py
ixexplorer/ixe_app.py
ixexplorer/ixe_hw.py
ixexplorer/ixe_object.py
ixexplorer/ixe_pg.py
ixexplorer/ixe_port.py
ixexplorer/ixe_statistics_view.py
ixexplorer/ixe_stream.py
ixexplorer/api/__init__.py
ixexplorer/api/ixapi.py
ixexplorer/api/tclproto.py
ixexplorer/data/IxExplorer_attributes.xml
ixexplorer/data/IxExplorer_commands.xml
ixexplorer/data/IxExplorer_options.xml
ixexplorer/samples/__init__.py
ixexplorer/samples/ixe_samples.py
ixexplorer/samples/tcl_cli.py
pyixexplorer-3.1.3.dist-info/METADATA
pyixexplorer-3.1.3.dist-info/WHEEL
pyixexplorer-3.1.3.dist-info/entry_points.txt
pyixexplorer-3.1.3.dist-info/top_level.txt
pyixexplorer-3.1.3.dist-info/RECORD
