Metadata-Version: 2.1
Name: pyixexplorer
Version: 3.1.3
Summary: Python OO API package to manage Ixia IxExplorer traffic generator
Home-page: https://github.com/shmir/PyIxExplorer/
Author: Yoram Shamir
Author-email: yoram@ignissoft.com
License: Apache Software License
Keywords: keysight,ixia,ixnetwork,ixload,spirent,testcenter,stc,avalanche,trex,xena,l2l3,l4l7,tg,traffic generator,test automation,automation api
Classifier: Development Status :: 5 - Production/Stable
Classifier: Natural Language :: English
Classifier: License :: OSI Approved :: Apache Software License
Classifier: Intended Audience :: Developers
Classifier: Operating System :: OS Independent
Classifier: Topic :: Software Development :: Testing
Classifier: Programming Language :: Python :: 3.7
Classifier: Programming Language :: Python :: 3.8
Classifier: Programming Language :: Python :: 3.9
Classifier: Programming Language :: Python :: 3.10
Requires-Dist: paramiko
Requires-Dist: pytrafficgen (<4.1.0,>=4.0.0)
